{
  "blocks": [
    {
      "key": "c0u3k",
      "data": {},
      "text": "Podczas gdy PiS ucieka od tematu aborcji, chcąc przeczekać do wyborów, Kaja Godek i Kościół naciskają na TK, by ustawę jeszcze zaostrzył, a PO przekonuje, że obecny \"kompromis\" jest święty, Polki i Polacy w swoich poglądach zbliżają się do Europy. W 2018 roku swoje ustawy zliberalizowały Cypr i Irlandia. Na naszym kontynencie aborcji z powodów społecznych lub na życzenie nie dopuszcza tylko Malta, Andora, Watykan. I Polska. ",
      "type": "unstyled",
      "depth": 0,
      "entityRanges": [],
      "inlineStyleRanges": []
    },
    {
      "key": "7avvq",
      "data": {},
      "text": "  ",
      "type": "atomic",
      "depth": 0,
      "entityRanges": [{ "key": 0, "length": 1, "offset": 0 }],
      "inlineStyleRanges": []
    },
    {
      "key": "52e7f",
      "data": {},
      "text": " ",
      "type": "unstyled",
      "depth": 0,
      "entityRanges": [],
      "inlineStyleRanges": []
    },
    {
      "key": "dfk3v",
      "data": {},
      "text": "  ",
      "type": "atomic",
      "depth": 0,
      "entityRanges": [{ "key": 1, "length": 1, "offset": 0 }],
      "inlineStyleRanges": []
    },
    {
      "key": "akka4",
      "data": {},
      "text": " \n ",
      "type": "atomic",
      "depth": 0,
      "entityRanges": [{ "key": 2, "length": 1, "offset": 0 }],
      "inlineStyleRanges": []
    },
    {
      "key": "bun0n",
      "data": {},
      "text": "  ",
      "type": "atomic",
      "depth": 0,
      "entityRanges": [{ "key": 3, "length": 1, "offset": 0 }],
      "inlineStyleRanges": []
    },
    {
      "key": "95vk3",
      "data": {},
      "text": "Sondaż pokazuje na słabnący wpływ katolickiej etyki, która od \"wzmożenia moralnego\" po śmierci Jana Pawła II w 2005 roku rządziła postawami. ",
      "type": "unstyled",
      "depth": 0,
      "entityRanges": [{ "key": 4, "length": 6, "offset": 0 }],
      "inlineStyleRanges": []
    },
    {
      "key": "86fk5",
      "data": {},
      "text": "Od 1993 roku (z półroczna przerwą w 1997) obowiązuje w Polsce restrykcyjna ustawa, która dopuszcza przerwanie ciąży w trzech wyjątkowych przypadkach: ratowania zdrowia i życia kobiety, gdy ciąża jest wynikiem gwałtu i gdy płód jest nieuleczalnie chory (przesłanka embriopatologiczna). Legalnych aborcji jest niewiele ponad 1000 rocznie, nielegalnych co najmniej kilkadziesiąt tysięcy. ",
      "type": "unstyled",
      "depth": 0,
      "entityRanges": [{ "key": 5, "length": 46, "offset": 337 }],
      "inlineStyleRanges": []
    },
    {
      "key": "e75b7",
      "data": {},
      "text": "  ",
      "type": "atomic",
      "depth": 0,
      "entityRanges": [{ "key": 6, "length": 1, "offset": 0 }],
      "inlineStyleRanges": []
    },
    {
      "key": "cqo55",
      "data": {},
      "text": " ",
      "type": "unstyled",
      "depth": 0,
      "entityRanges": [],
      "inlineStyleRanges": []
    },
    {
      "key": "2q372",
      "data": {},
      "text": " \n ",
      "type": "atomic",
      "depth": 0,
      "entityRanges": [{ "key": 7, "length": 1, "offset": 0 }],
      "inlineStyleRanges": []
    },
    {
      "key": "6gdjj",
      "data": {},
      "text": "  ",
      "type": "atomic",
      "depth": 0,
      "entityRanges": [{ "key": 8, "length": 1, "offset": 0 }],
      "inlineStyleRanges": []
    },
    {
      "key": "7s57a",
      "data": {},
      "text": "Z sondażu IPSOS dla OKO.press wynika jednak, że aż 53 proc. Polek i Polaków jest zdania, że kobieta powinna mieć prawo do aborcji w pierwszych 12 tygodniach ciąży, bez względu na okoliczności. ",
      "type": "unstyled",
      "depth": 0,
      "entityRanges": [],
      "inlineStyleRanges": []
    },
    {
      "key": "4kc48",
      "data": {},
      "text": "  ",
      "type": "atomic",
      "depth": 0,
      "entityRanges": [{ "key": 9, "length": 1, "offset": 0 }],
      "inlineStyleRanges": []
    },
    {
      "key": "9lv8p",
      "data": {},
      "text": "Pytanie, które skupia uwagę na prawie kobiety do decyzji, zadaliśmy po raz pierwszy. We wcześniejszych sondażach konfrontowaliśmy badanych z obowiązującą ustawą antyaborcyjną i pytaliśmy, czy należałoby ją zliberalizować (\"dopuszczając aborcję także z powodu trudnej sytuacji kobiety\"), zaostrzyć, czy pozostawić bez zmian. W sierpniu 2018 roku za liberalizacją opowiedziało się 38 proc., a za pozostawieniem ustawy bez zmian - 44 proc. ",
      "type": "unstyled",
      "depth": 0,
      "entityRanges": [{ "key": 10, "length": 27, "offset": 85 }],
      "inlineStyleRanges": []
    },
    {
      "key": "8pr88",
      "data": {},
      "text": "[tab tekst=\"Zobacz wyniki poprzednich sondaży\"] ",
      "type": "unstyled",
      "depth": 0,
      "entityRanges": [],
      "inlineStyleRanges": []
    },
    {
      "key": "6a8ao",
      "data": {},
      "text": "  ",
      "type": "atomic",
      "depth": 0,
      "entityRanges": [{ "key": 11, "length": 1, "offset": 0 }],
      "inlineStyleRanges": []
    },
    {
      "key": "858ok",
      "data": {},
      "text": "[/tab] ",
      "type": "unstyled",
      "depth": 0,
      "entityRanges": [],
      "inlineStyleRanges": []
    },
    {
      "key": "4p4qr",
      "data": {},
      "text": "W obecnym, lutowym sondażu widać dużą różnicę w odpowiedziach mężczyzn i kobiet. Aż 57 proc. respondentek opowiedziało się za prawem do przerwania ciąży. Mniej - 49 proc. - mężczyzn wybrało tę odpowiedź. Co ciekawe, odsetek odpowiedzi \"nie\" jest taki sam w obu grupach, ale prawie dwa razy więcej mężczyzn niż kobiet wybrało odpowiedź \"nie wiem\". ",
      "type": "unstyled",
      "depth": 0,
      "entityRanges": [],
      "inlineStyleRanges": []
    },
    {
      "key": "3ut3l",
      "data": {},
      "text": "  ",
      "type": "atomic",
      "depth": 0,
      "entityRanges": [{ "key": 12, "length": 1, "offset": 0 }],
      "inlineStyleRanges": []
    },
    {
      "key": "627ji",
      "data": {},
      "text": "Podobnie było w sondażu z kwietnia 2018 roku, gdy poza standardowym pytaniem o liberalizację/zaostrzenie zadaliśmy jeszcze jedno: \"Proszę sobie wyobrazić, że Pana/Pani bliska znajoma chce przerwać ciążę z powodu trudnej sytuacji osobistej. Czy uważa Pan\\i, że prawo powinno jej tego zakazywać, czy nie\". ",
      "type": "unstyled",
      "depth": 0,
      "entityRanges": [{ "key": 13, "length": 28, "offset": 16 }],
      "inlineStyleRanges": []
    },
    {
      "key": "4sdt4",
      "data": {},
      "text": "Chcieliśmy odwołać się do \"etyki życia codziennego\", kiedy abstrakcyjne zasady konfrontują się z prawdziwym doświadczeniem. Wynik tamtego sondażu był podobny do dziś omawianego - 55 proc. uznało, że prawo nie powinno aborcji zakazywać, przy czym takiej odpowiedzi udzieliło aż 60 proc. kobiet i 50 proc. mężczyzn. ",
      "type": "unstyled",
      "depth": 0,
      "entityRanges": [],
      "inlineStyleRanges": []
    },
    {
      "key": "3mo9s",
      "data": {},
      "text": "  ",
      "type": "atomic",
      "depth": 0,
      "entityRanges": [{ "key": 14, "length": 1, "offset": 0 }],
      "inlineStyleRanges": []
    },
    {
      "key": "eaomv",
      "data": {},
      "text": "PO w tyle za swoimi wyborcami ",
      "type": "header-two",
      "depth": 0,
      "entityRanges": [],
      "inlineStyleRanges": []
    },
    {
      "key": "2mv0r",
      "data": {},
      "text": "PO jak mantrę powtarza, że nie chce zmieniać ustawy antyaborcyjnej, uzasadniając to m.in. poglądami swoich wyborców. Dołączenie do koalicji z PO na czele Barbary Nowackiej, do niedawna twarzy projektów liberalizujących przepisy, nic w tej kwestii nie zmieniło. W styczniu 2018 roku projekt Nowackiej \"Ratujmy kobiety\" przepadł w Sejmie w pierwszym czytaniu zaledwie dziewięcioma głosami. Prawie 30 posłów opozycji z głosowania uciekło. W 2016 Grzegorz Schetyna proponował nawet wpisanie \"kompromisu\" do konstytucji. ",
      "type": "unstyled",
      "depth": 0,
      "entityRanges": [{ "key": 15, "length": 39, "offset": 395 }],
      "inlineStyleRanges": []
    },
    {
      "key": "5vclp",
      "data": {},
      "text": "Z naszego najnowszego sondażu wynika - nie pierwszy raz - że elektorat partii jest dużo bardziej liberalny niż politycy. ",
      "type": "blockquote",
      "depth": 0,
      "entityRanges": [],
      "inlineStyleRanges": []
    },
    {
      "key": "3q9c",
      "data": {},
      "text": "Aż 80 proc. wyborców PO wybrało odpowiedź \"tak\", a tylko 12 proc. \"nie\". Najbardziej liberalny jest elektorat Wiosny, ale różnica między wyborcami PO i Wiosny jest zaskakująco niewielka. Robert Biedroń, w przeciwieństwie do PO, wyraźnie akcentuje potrzebę liberalizacji ustawy - aborcja do 12. tygodnia znalazła się w jego programie wyborczym. ",
      "type": "unstyled",
      "depth": 0,
      "entityRanges": [],
      "inlineStyleRanges": []
    },
    {
      "key": "2mbo8",
      "data": {},
      "text": "  ",
      "type": "atomic",
      "depth": 0,
      "entityRanges": [{ "key": 16, "length": 1, "offset": 0 }],
      "inlineStyleRanges": []
    },
    {
      "key": "11tcc",
      "data": {},
      "text": "Zaskakująco liberalny - dużo bardziej niż konserwatywna partia - jest też elektorat PSL. Szef PSL Władysław Kosiniak-Kamysz deklarował nawet w 2017 roku, że jest za zaostrzeniem ustawy (usunięciem przesłanki embriopatologicznej). Tymczasem aż 60 proc. wyborców wybrało odpowiedź \"tak\". ",
      "type": "blockquote",
      "depth": 0,
      "entityRanges": [{ "key": 17, "length": 28, "offset": 156 }],
      "inlineStyleRanges": []
    },
    {
      "key": "32fjq",
      "data": {},
      "text": "Najbardziej konserwatywny jest oczywiście elektorat PiS, jednak i tu wynik na \"tak\" jest stosunkowo duży (jak na partię skrajnie prawicową i odwołującą się w programie do nauki Kościoła) - 21 proc. ",
      "type": "unstyled",
      "depth": 0,
      "entityRanges": [],
      "inlineStyleRanges": []
    },
    {
      "key": "fig4l",
      "data": {},
      "text": "Na wykresie nie ma elektoratu Nowoczesnej i partii Teraz!, gdyż ich elektorat w naszym sondażu był za mały, żeby wyciągać jakiekolwiek wnioski. Warto jednak zaznaczyć, że to posłanki obu tych partii jeszcze w 2017 roku zgłosiły swój własny projekt liberalizacji ustawy antyaborcyjnej. Zakładał on, podobnie, jak projekt Nowackiej, że aborcja będzie legalna do 12. tygodnia ciąży, ale po konsultacji z psychologiem. W styczniu 2018 roku, po porażce \"Ratujmy kobiety\", Nowoczesna wraz z PSL i Unią Europejskich Demokratów złożyła w Sejmie projekt Nowackiej (chodziło o to, by projekt nie przepadł, co się zresztą nie udało). Także SLD ma w programie aborcję na życzenie. ",
      "type": "unstyled",
      "depth": 0,
      "entityRanges": [
        { "key": 18, "length": 42, "offset": 64 },
        { "key": 19, "length": 30, "offset": 348 },
        { "key": 20, "length": 89, "offset": 467 }
      ],
      "inlineStyleRanges": []
    },
    {
      "key": "dai90",
      "data": {},
      "text": "Nasz sondaż pozwolił również sprawdzić poglądy elektoratu całej ogłoszonej 1 lutego Koalicji Europejskiej (która osiągnęła poparcie 33 proc. remisując statystycznie z PiS - 34 proc.). ",
      "type": "unstyled",
      "depth": 0,
      "entityRanges": [],
      "inlineStyleRanges": []
    },
    {
      "key": "c2kcs",
      "data": {},
      "text": "Obecność w elektoracie Koalicji Europejskiej zwolenników PSL tylko nieznacznie obniża ogromne poparcie dla prawa kobiety do przerywania ciąży: 78 proc. - za, 13 proc. - przeciw. ",
      "type": "blockquote",
      "depth": 0,
      "entityRanges": [],
      "inlineStyleRanges": []
    },
    {
      "key": "9lgsl",
      "data": {},
      "text": "Młodzi i starzy konserwatywni ",
      "type": "header-two",
      "depth": 0,
      "entityRanges": [],
      "inlineStyleRanges": []
    },
    {
      "key": "9hr03",
      "data": {},
      "text": "Wyniki sondażu w grupach wiekowych nie potwierdzają naszego wniosku z kwietnia 2018 roku, gdy wydawało się, że najmłodsi stają się coraz bardziej liberalni. Wynik najnowszego sondażu przypomina ten ze stycznia 2018 - przeciw prawu do aborcji do 12. tygodnia są najczęściej najmłodsi i najstarsi. \"Tak\" najczęściej odpowiadały osoby w wieku 40-49 lat (63 proc.) i 30-39 (60 proc.). ",
      "type": "unstyled",
      "depth": 0,
      "entityRanges": [{ "key": 21, "length": 44, "offset": 111 }],
      "inlineStyleRanges": []
    },
    {
      "key": "26o7m",
      "data": {},
      "text": "Odpowiedzi pokolenia 60 plus wyjaśnić można faktem, że ta grupa wiekowa najczęściej głosuje na konserwatywny PiS oraz najczęściej podziela wykładnię Kościoła katolickiego. ",
      "type": "unstyled",
      "depth": 0,
      "entityRanges": [],
      "inlineStyleRanges": []
    },
    {
      "key": "8mfti",
      "data": {},
      "text": "Wynik w najmłodszej grupie może oznaczać, że katolicka i konserwatywna narracja, obecna we wszystkich instytucjach publicznych m.in. w szkołach, zaczyna przynosić efekty. ",
      "type": "blockquote",
      "depth": 0,
      "entityRanges": [],
      "inlineStyleRanges": []
    },
    {
      "key": "aro6m",
      "data": {},
      "text": "Trzeba jednak podkreślić, że we wszystkich grupach odsetek odpowiedzi \"tak\" przewyższał \"nie\". ",
      "type": "unstyled",
      "depth": 0,
      "entityRanges": [],
      "inlineStyleRanges": []
    },
    {
      "key": "2qonq",
      "data": {},
      "text": "  ",
      "type": "atomic",
      "depth": 0,
      "entityRanges": [{ "key": 22, "length": 1, "offset": 0 }],
      "inlineStyleRanges": []
    },
    {
      "key": "4jc3d",
      "data": {},
      "text": "Zgoda na aborcję rośnie wraz z poziomem wykształcenia. Jedynie wśród osób z wykształceniem podstawowym więcej było odpowiedzi \"nie\", w innych grupach przeważała postawa pro-choice. W grupie z wyższym wykształceniem przewaga była dwukrotna. ",
      "type": "unstyled",
      "depth": 0,
      "entityRanges": [],
      "inlineStyleRanges": []
    },
    {
      "key": "fg30r",
      "data": {},
      "text": "  ",
      "type": "atomic",
      "depth": 0,
      "entityRanges": [{ "key": 23, "length": 1, "offset": 0 }],
      "inlineStyleRanges": []
    },
    {
      "key": "dv8s0",
      "data": {},
      "text": "Gdy w poprzednich sondażach pytaliśmy o liberalizację/zaostrzenie, osoby z wykształceniem wyższym zazwyczaj opowiadały się za pozostawieniem ustawy bez zmian. Najbardziej liberalni byli respondenci z wykształceniem zawodowym. Teraz zaprezentowali postawy nieco bardziej konserwatywne. Gdy w kwietniu 2018 zadaliśmy pytanie o bliską osobę w trudnej sytuacji, odpowiedzi przypominały te z najnowszego sondażu - przyzwolenie na aborcję rosło wraz z poziomem wykształcenia. ",
      "type": "unstyled",
      "depth": 0,
      "entityRanges": [
        { "key": 24, "length": 59, "offset": 6 },
        { "key": 25, "length": 51, "offset": 305 }
      ],
      "inlineStyleRanges": []
    },
    {
      "key": "bal19",
      "data": {},
      "text": "To może oznaczać, że ludzi z wyższym wykształceniem cechuje duża rozbieżność między deklarowanymi wartościami, a etyką dnia codziennego, która ma wpływ na zachowania. ",
      "type": "blockquote",
      "depth": 0,
      "entityRanges": [],
      "inlineStyleRanges": []
    },
    {
      "key": "9tf7t",
      "data": {},
      "text": "Mieszkańcy miast - i średnich, i dużych - opowiadają się za prawem do aborcji. Najczęściej ci mieszkający w mieście od 100 tys. do 500 tys. mieszkańców (64 proc.). W większych miastach (od 20 tys.) przeciwników prawa do aborcji jest ponad dwa razy mniej, niż zwolenników. Wśród mieszkańców wsi jest remis - odpowiedzi \"tak\" i \"nie\" wybrało po 43 proc. respondentów. ",
      "type": "unstyled",
      "depth": 0,
      "entityRanges": [],
      "inlineStyleRanges": []
    },
    {
      "key": "9ofkp",
      "data": {},
      "text": "Te wyniki coś nam przypominają. Wracamy do roku 2002 ",
      "type": "header-two",
      "depth": 0,
      "entityRanges": [],
      "inlineStyleRanges": []
    },
    {
      "key": "duv1n",
      "data": {},
      "text": "Nie tak dawno prawo do aborcji było w Polsce - i poglądach Polek i Polaków - oczywistością. ",
      "type": "unstyled",
      "depth": 0,
      "entityRanges": [],
      "inlineStyleRanges": []
    },
    {
      "key": "daskj",
      "data": {},
      "text": "W momencie transformacji Polska miała jedną z najbardziej liberalnych ustaw aborcyjnych w Europie. Aborcja była dozwolona ze względu na trudną sytuację kobiety, co dawało w zasadzie nieograniczone możliwości przerwania niechcianej ciąży. W 1993 roku, mimo ogromnego sprzeciwu społecznego, politycy drastycznie zaostrzyli przepisy dotyczące aborcji, które obowiązują do dzisiaj. ",
      "type": "unstyled",
      "depth": 0,
      "entityRanges": [],
      "inlineStyleRanges": []
    },
    {
      "key": "44d0k",
      "data": {},
      "text": "Od 1990 roku do momentu zaostrzenia ustawy antyaborcyjnej systematycznie wzrastała liczba zwolenników prawa do aborcji bez ograniczeń, a malała liczba zwolenników całkowitego zakazu. ",
      "type": "blockquote",
      "depth": 0,
      "entityRanges": [{ "key": 26, "length": 24, "offset": 58 }],
      "inlineStyleRanges": []
    },
    {
      "key": "8nkh4",
      "data": {},
      "text": "Po decyzji Sejmu poparcie dla prawa do aborcji zaczęło spadać, ale postawy pro-choice ciągle dominowały. Dopiero w latach 2005-2006 nastąpił gwałtowny wzrost postaw konserwatywnych. Powodem tego wzmożenia mogła być śmierć Jana Pawła II (kwiecień 2005), który mocno opowiadał się przeciw aborcji oraz wygrana PiS (wrzesień 2005), który szedł do wyborów z hasłem \"rewolucji moralnej\". ",
      "type": "unstyled",
      "depth": 0,
      "entityRanges": [],
      "inlineStyleRanges": []
    },
    {
      "key": "2fr8j",
      "data": {},
      "text": "Dobrze widać to na poniższym wykresie. Pytanie zadane przez CBOS jest podobne do tego, które zadaliśmy w najnowszym sondażu: ",
      "type": "unstyled",
      "depth": 0,
      "entityRanges": [],
      "inlineStyleRanges": []
    },
    {
      "key": "cvucg",
      "data": {},
      "text": "  ",
      "type": "atomic",
      "depth": 0,
      "entityRanges": [{ "key": 27, "length": 1, "offset": 0 }],
      "inlineStyleRanges": []
    },
    {
      "key": "7t1lr",
      "data": {},
      "text": "Widać także, że jeszcze w 1997 roku przewaga zwolenników prawa do aborcji była ponad dwukrotna. Wyniki naszego sondażu są statystycznie identyczne z wynikiem CBOS października 2002 (54 proc. - za, 32 proc. - przeciw, 12 proc. niezdecydowanych). ",
      "type": "unstyled",
      "depth": 0,
      "entityRanges": [],
      "inlineStyleRanges": []
    },
    {
      "key": "6qegb",
      "data": {},
      "text": "Zobacz analizę, jak kształtowały się postawy Polaków w kwestii aborcji: ",
      "type": "unstyled",
      "depth": 0,
      "entityRanges": [],
      "inlineStyleRanges": []
    },
    {
      "key": "6ioko",
      "data": {},
      "text": "   ",
      "type": "atomic",
      "depth": 0,
      "entityRanges": [{ "key": 28, "length": 1, "offset": 0 }],
      "inlineStyleRanges": []
    },
    {
      "key": "fjm65",
      "data": {},
      "text": "Sondaż IPSOS dla OKO.press 14-16 lutego 2019, metodą CATI (telefonicznie), na ogólnopolskiej reprezentatywnej próbie 1004 osób.  ",
      "type": "unstyled",
      "depth": 0,
      "entityRanges": [],
      "inlineStyleRanges": [{ "style": "ITALIC", "length": 127, "offset": 0 }]
    },
    {
      "key": "56t53",
      "data": {},
      "text": "",
      "type": "unstyled",
      "depth": 0,
      "entityRanges": [],
      "inlineStyleRanges": []
    },
    {
      "key": "f7qka",
      "data": {},
      "text": "",
      "type": "unstyled",
      "depth": 0,
      "entityRanges": [],
      "inlineStyleRanges": []
    }
  ],
  "entityMap": {
    "0": {
      "data": { "title": "Zobacz mapy świata i Europy prawa do aborcji " },
      "type": "EXPAND_START",
      "mutability": "IMMUTABLE"
    },
    "1": {
      "data": {
        "alt": "",
        "src": "https://oko.press/images/2019/03/Zrzut-ekranu-2019-03-01-o-09.46.48-300x193.png",
        "width": "",
        "height": ""
      },
      "type": "IMAGE",
      "mutability": "MUTABLE"
    },
    "2": {
      "data": {
        "alt": "",
        "src": "https://oko.press/images/2019/03/Zrzut-ekranu-2019-03-01-o-09.47.07-300x197.png",
        "width": "",
        "height": ""
      },
      "type": "IMAGE",
      "mutability": "MUTABLE"
    },
    "3": { "data": {}, "type": "EXPAND_END", "mutability": "IMMUTABLE" },
    "4": {
      "data": {
        "slug": "kategoria/analizy-sondaze",
        "type": "LEGACY_INTERNAL"
      },
      "type": "LINK",
      "mutability": "MUTABLE"
    },
    "5": {
      "data": { "slug": "polek-przerywa-ciaze", "type": "LEGACY_INTERNAL" },
      "type": "LINK",
      "mutability": "MUTABLE"
    },
    "6": {
      "data": { "title": "Zobacz wykres liczby legalnych aborcji" },
      "type": "EXPAND_START",
      "mutability": "IMMUTABLE"
    },
    "7": {
      "data": {
        "alt": "",
        "src": "https://oko.press/images/2019/03/Zrzut-ekranu-2019-03-01-o-09.56.29-300x201.png",
        "width": "",
        "height": ""
      },
      "type": "IMAGE",
      "mutability": "MUTABLE"
    },
    "8": { "data": {}, "type": "EXPAND_END", "mutability": "IMMUTABLE" },
    "9": {
      "data": {
        "id": "8060da24-5df1-455a-aa72-66bd9afe0e0d",
        "layout": "column"
      },
      "type": "IMAGE",
      "mutability": "IMMUTABLE"
    },
    "10": {
      "data": {
        "slug": "kategoria/analizy-sondaze",
        "type": "LEGACY_INTERNAL"
      },
      "type": "LINK",
      "mutability": "MUTABLE"
    },
    "11": {
      "data": {
        "id": "78353f9e-2d1a-4fb0-b1e0-26ad5ac9839d",
        "layout": "column"
      },
      "type": "IMAGE",
      "mutability": "IMMUTABLE"
    },
    "12": {
      "data": {
        "id": "6abe1fc9-e166-43f0-8070-565a89eb0fd2",
        "layout": "column"
      },
      "type": "IMAGE",
      "mutability": "IMMUTABLE"
    },
    "13": {
      "data": {
        "slug": "az-60-proc-polek-i-50-proc-polakow-uwaza-ze-prawo-powinno-zezwalac-na-przerwanie-ciazy-znajomej-kobiecie",
        "type": "LEGACY_INTERNAL"
      },
      "type": "LINK",
      "mutability": "MUTABLE"
    },
    "14": {
      "data": { "nodes": ["213ed3dd-800d-4b9b-abab-8a99e4e3cba7"] },
      "type": "RELATED_CONTENTS",
      "mutability": "IMMUTABLE"
    },
    "15": {
      "data": {
        "slug": "sejm-odrzucil-ratujmy-kobiety-a-zatrzymaj-aborcje-trafil-komisji-gdyby-stawilo-sie-pelnym-skladzie-projekt-nowackiej-zostalby-sejmie",
        "type": "LEGACY_INTERNAL"
      },
      "type": "LINK",
      "mutability": "MUTABLE"
    },
    "16": {
      "data": {
        "id": "9fe59627-4239-4f11-873c-07ed4be1bade",
        "layout": "column"
      },
      "type": "IMAGE",
      "mutability": "IMMUTABLE"
    },
    "17": {
      "data": {
        "url": "http://wyborcza.pl/7,75398,22376615,wladyslaw-kosiniak-kamysz-dla-dgp-zakazalbym-aborcji-eugenicznej.html",
        "type": "EXTERNAL"
      },
      "type": "LINK",
      "mutability": "MUTABLE"
    },
    "18": {
      "data": {
        "slug": "koalicja-europejska-332-proc-dogonila-pis-337-i-razem-z-wiosna-12-moglaby-go-odsunac-od-wladzy",
        "type": "LEGACY_INTERNAL"
      },
      "type": "LINK",
      "mutability": "MUTABLE"
    },
    "19": {
      "data": {
        "slug": "nowoczesna-chce-dac-kobietom-prawo-do-przerywania-ciazy-ale-tylko-po-kosultacji-jak-niemczech",
        "type": "LEGACY_INTERNAL"
      },
      "type": "LINK",
      "mutability": "MUTABLE"
    },
    "20": {
      "data": {
        "slug": "ratujmy-kobiety-wroca-sejmu-zlozy-go-nowoczesna-europejscy-demokraci-poslanka-psl-przeciw-zrobi-pis-tym-razem",
        "type": "LEGACY_INTERNAL"
      },
      "type": "LINK",
      "mutability": "MUTABLE"
    },
    "21": {
      "data": {
        "slug": "az-60-proc-polek-i-50-proc-polakow-uwaza-ze-prawo-powinno-zezwalac-na-przerwanie-ciazy-znajomej-kobiecie",
        "type": "LEGACY_INTERNAL"
      },
      "type": "LINK",
      "mutability": "MUTABLE"
    },
    "22": {
      "data": {
        "id": "98ef7504-7314-43c7-9bd5-3bc1b16682f2",
        "layout": "column"
      },
      "type": "IMAGE",
      "mutability": "IMMUTABLE"
    },
    "23": {
      "data": {
        "id": "4439d8f1-2e9c-416d-b133-811fd3fcb7be",
        "layout": "column"
      },
      "type": "IMAGE",
      "mutability": "IMMUTABLE"
    },
    "24": {
      "data": {
        "slug": "37-proc-polakow-liberalizacja-ustawy-antyaborcyjnej-15-proc-calkowitym-zakazem-elektoraty-odwazniejsze-niz-liderzy-sondazu-oko-press",
        "type": "LEGACY_INTERNAL"
      },
      "type": "LINK",
      "mutability": "MUTABLE"
    },
    "25": {
      "data": {
        "slug": "az-60-proc-polek-i-50-proc-polakow-uwaza-ze-prawo-powinno-zezwalac-na-przerwanie-ciazy-znajomej-kobiecie",
        "type": "LEGACY_INTERNAL"
      },
      "type": "LINK",
      "mutability": "MUTABLE"
    },
    "26": {
      "data": {
        "url": "http://www.cbos.pl/SPISKOM.POL/1992/K_104_92.PDF",
        "type": "EXTERNAL"
      },
      "type": "LINK",
      "mutability": "MUTABLE"
    },
    "27": {
      "data": {
        "id": "1de9524d-340c-4d57-87cf-2836782f85ba",
        "layout": "column"
      },
      "type": "IMAGE",
      "mutability": "IMMUTABLE"
    },
    "28": {
      "data": { "nodes": ["6bed0d13-44db-40f4-8481-4b415bb8cd76"] },
      "type": "RELATED_CONTENTS",
      "mutability": "IMMUTABLE"
    }
  }
}
